verba/Embedder.py
verba/Generator.py
verba/OllamaHelper.py
verba/__init__.py
verba-0.2.1.dist-info/licenses/LICENSE.md
verba-0.2.1.dist-info/METADATA
verba-0.2.1.dist-info/WHEEL
verba-0.2.1.dist-info/top_level.txt
verba-0.2.1.dist-info/RECORD
