Metadata-Version: 2.4
Name: verba
Version: 0.2.1
Summary: A collection of modules used for language processing and modeling
Home-page: https://codeberg.org/tomathon/verba
Author: tomathon
Author-email: tomathon@pm.me
License: GPL-3
Project-URL: Bug Tracker, https://codeberg.org/tomathon/verba/issues
Classifier: Programming Language :: Python :: 3
Classifier: License :: OSI Approved :: MIT License
Classifier: Operating System :: OS Independent
Requires-Python: >=3.8
License-File: LICENSE.md
Dynamic: license-file
